iSparrowRecord/__init__.py
iSparrowRecord/audio_recording.py
iSparrowRecord/cli.py
iSparrowRecord/runner.py
iSparrowRecord/set_up.py
iSparrowRecord/utils.py
isparrowrecord-0.0.8a0.dist-info/LICENSE
isparrowrecord-0.0.8a0.dist-info/METADATA
isparrowrecord-0.0.8a0.dist-info/WHEEL
isparrowrecord-0.0.8a0.dist-info/entry_points.txt
isparrowrecord-0.0.8a0.dist-info/top_level.txt
isparrowrecord-0.0.8a0.dist-info/RECORD
