Metadata-Version: 2.1
Name: isparrowrecord
Version: 0.0.8a0
Summary: Audio Recording Facilities for the isparrow package
Author-email: Inga Ulusoy <inga.ulusoy@uni-heidelberg.de>, Harald Mack <harald.mack@iwr.uni-heidelberg.de>
License: Apache License
Project-URL: Repository, https://github.com/ssciwr/iSparrowRecord
Classifier: Programming Language :: Python :: 3
Classifier: Operating System :: OS Independent
Classifier: License :: OSI Approved :: Apache Software License
Requires-Python: >=3.9
License-File: LICENSE
Requires-Dist: numpy
Requires-Dist: librosa
Requires-Dist: PyYAML
Requires-Dist: wave
Requires-Dist: pyaudio
Requires-Dist: platformdirs
Requires-Dist: click
